spc_io/__init__.py
spc_io/__main__.py
spc_io/high_level/__init__.py
spc_io/high_level/even_axis.py
spc_io/high_level/log_book.py
spc_io/high_level/spc.py
spc_io/low_level/__init__.py
spc_io/low_level/spc_raw.py
spc_io/low_level/sub_file.py
spc_io/low_level/xarray_property.py
spc_io/low_level/headers/__init__.py
spc_io/low_level/headers/fdate.py
spc_io/low_level/headers/fexper.py
spc_io/low_level/headers/fmods.py
spc_io/low_level/headers/ftflgs.py
spc_io/low_level/headers/fversn.py
spc_io/low_level/headers/fxytype.py
spc_io/low_level/headers/logstc.py
spc_io/low_level/headers/spchdr.py
spc_io/low_level/headers/ssfstc.py
spc_io/low_level/headers/sub_hdr.py
spc_io/misc/__init__.py
spc_io/misc/enum_type.py
spc_io/misc/struct_enum_type.py
spc_io-0.2.1.dist-info/licenses/LICENSE
spc_io-0.2.1.dist-info/METADATA
spc_io-0.2.1.dist-info/WHEEL
spc_io-0.2.1.dist-info/top_level.txt
spc_io-0.2.1.dist-info/RECORD
