Metadata-Version: 2.4
Name: spc-io
Version: 0.2.1
Summary: SPC file format parser
Home-page: https://github.com/h2020charisma/spc-io
Author: IDEAconsult Ltd.
Author-email: dev-charisma@ideaconsult.net
License: MIT
Keywords: Raman,spectroscopy
Classifier: Development Status :: 4 - Beta
Classifier: Intended Audience :: Developers
Classifier: Intended Audience :: Education
Classifier: Intended Audience :: Science/Research
Classifier: License :: OSI Approved :: MIT License
Classifier: Operating System :: OS Independent
Classifier: Programming Language :: Python :: 3 :: Only
Classifier: Programming Language :: Python :: 3
Classifier: Programming Language :: Python
Classifier: Topic :: Scientific/Engineering :: Bio-Informatics
Classifier: Topic :: Scientific/Engineering
Classifier: Topic :: Software Development :: Libraries :: Python Modules
Classifier: Topic :: Software Development :: Libraries
Requires-Python: ~=3.8
License-File: LICENSE
Requires-Dist: numpy
Requires-Dist: pydantic~=2.0
Requires-Dist: pandas
Dynamic: license-file
